skserve/ModelServer.py
skserve/__init__.py
skserve-0.11.dist-info/LICENSE
skserve-0.11.dist-info/METADATA
skserve-0.11.dist-info/WHEEL
skserve-0.11.dist-info/top_level.txt
skserve-0.11.dist-info/RECORD
