Metadata-Version: 2.1
Name: skserve
Version: 0.11
Summary: Flask-derived wrapper to serve sklearn models
Home-page: https://github.com/adamgrbac/skserve
Author: Adam Michael Grbac
Author-email: adam.grbac@gmail.com
License: MIT
Platform: UNKNOWN
Classifier: Development Status :: 1 - Planning
Classifier: License :: OSI Approved :: MIT License
Classifier: Programming Language :: Python :: 3
Classifier: Topic :: Scientific/Engineering
Requires-Dist: sklearn
Requires-Dist: flask
Requires-Dist: pandas
